{
    "slug": "aok",
    "relevant-countries": [
        "de"
    ],
    "categories": [
        "insurance"
    ],
    "name": "AOK NordWest",
    "address": "AOK NordWest\nDie Gesundheitskasse.\n58079 Hagen",
    "phone": "0800 265 5000",
    "fax": "0800 265 2265",
    "webform": "https://www.aok.de/pk/kontakt/kontaktformular/",
    "web": "https://www.aok.de/pk/nordwest/",
    "sources": [
        "https://www.aok.de/pk/nordwest/",
        "https://www.aok.de/pk/rechtliches/kontakt-datenschutzbeauftragter/",
        "https://github.com/datenanfragen/data/pull/2844"
    ],
    "suggested-transport-medium": "webform",
    "quality": "verified"
}
