{
    "slug": "bondora",
    "relevant-countries": [
        "all"
    ],
    "categories": [
        "finance"
    ],
    "name": "Bondora Capital OÜ",
    "runs": [
        "bondora.com"
    ],
    "address": "A. H. Tammsaare tee 47\nTallinn 11316\nEstonia",
    "email": "investor@bondora.com",
    "web": "https://www.bondora.com/en/",
    "sources": [
        "https://www.bondora.com/en/terms#privacy-policy",
        "https://github.com/datenanfragen/data/pull/1652"
    ],
    "required-elements": [
        {
            "desc": "Username",
            "type": "email",
            "optional": false
        }
    ],
    "suggested-transport-medium": "letter",
    "quality": "verified"
}
