{
    "slug": "bonprix",
    "relevant-countries": [
        "de"
    ],
    "categories": [
        "commerce"
    ],
    "name": "bonprix Handelsgesellschaft mbH",
    "address": "Haldesdorfer Straße 61\n22179 Hamburg\nDeutschland",
    "phone": "+49 40 64620",
    "fax": "+49 40 64623700",
    "email": "datenschutz@bonprix.net",
    "web": "https://www.bonprix.de/",
    "sources": [
        "https://www.bonprix.de/service/datenschutz/",
        "https://www.bonprix.de/service/impressum/"
    ],
    "suggested-transport-medium": "email",
    "quality": "verified"
}
