{
    "slug": "dance-all-day",
    "relevant-countries": [
        "de"
    ],
    "categories": [
        "entertainment"
    ],
    "name": "Dance All Day Musicvertriebs GmbH",
    "runs": [
        "feiyr.com",
        "djshop.de (ehem.)"
    ],
    "address": "Raiffeisenstr 4\n83377 Vachendorf\nDeutschland",
    "phone": "+49 861 166170",
    "email": "datenschutz@dance-all-day.com",
    "webform": "legal@bigo.tv/feedback@bigo.tv",
    "web": "https://www.dance-all-day.com",
    "sources": [
        "https://github.com/datenanfragen/data/pull/2364",
        "https://github.com/datenanfragen/data/pull/3075"
    ],
    "suggested-transport-medium": "email",
    "quality": "verified"
}
