{
    "slug": "deutsche-post-direkt",
    "categories": [
        "addresses"
    ],
    "name": "Deutsche Post Direkt GmbH",
    "address": "Junkersring 57\n53844 Troisdorf\nDeutschland",
    "phone": "+49 800 936 937 3",
    "fax": "+49 2241 2661 1111",
    "email": "datenservice@postdirekt.de",
    "web": "https://service.postdirekt.de/pdportal/PublicServlet",
    "sources": [
        "https://service.postdirekt.de/pdportal/PublicServlet?command=content&page=datenschutz",
        "https://service.postdirekt.de/pdportal/PublicServlet?command=content&page=impressum"
    ],
    "required-elements": [
        {
            "desc": "Name",
            "type": "name"
        },
        {
            "desc": "Adresse",
            "type": "address"
        }
    ],
    "relevant-countries": [
        "de"
    ]
}
