{
    "slug": "deutsche-post-direkt",
    "relevant-countries": [
        "de"
    ],
    "categories": [
        "addresses"
    ],
    "name": "Deutsche Post Direkt GmbH",
    "address": "Junkersring 57\n53844 Troisdorf\nDeutschland",
    "phone": "+49 2241 2661 2680",
    "fax": "+49 2241 2661 6680",
    "email": "datenschutz@postdirekt.de",
    "sources": [
        "https://github.com/datenanfragen/data/pull/1668"
    ],
    "required-elements": [
        {
            "desc": "Name",
            "type": "name"
        },
        {
            "desc": "Adresse",
            "type": "address"
        }
    ],
    "needs-id-document": false,
    "suggested-transport-medium": "email",
    "quality": "tested"
}
