{
    "slug": "g2a",
    "relevant-countries": [
        "all"
    ],
    "categories": [
        "entertainment"
    ],
    "name": "G2A.COM Limited",
    "address": "DPO\nG2A.COM Limited\n31/F, Tower Two,\nTimes Square,\n1 Matheson Street,\nCauseway Bay,\nHong Kong",
    "email": "dpo@g2a.com",
    "web": "https://g2a.com",
    "sources": [
        "https://www.g2a.com/privacy-policy?___store=english",
        "https://github.com/datenanfragen/data/pull/768"
    ],
    "needs-id-document": false,
    "suggested-transport-medium": "email",
    "quality": "verified"
}
