{
    "slug": "gsonfa36c00mbrr",
    "relevant-countries": [
        "it"
    ],
    "categories": [
        "utility"
    ],
    "name": "GSONFA36C00MBRR",
    "runs": [],
    "address": "Elisabetta fontana via julia augusta cervignano del friuli 33050 , Ud itaky",
    "phone": "3207160121",
    "email": "betta10fonta@yahoo.it",
    "sources": [
        "Order",
        "https://github.com/datenanfragen/data/pull/2535"
    ],
    "suggested-transport-medium": "email",
    "comments": [
        "Where my order GSONFA36C00MBRR"
    ],
    "quality": "verified"
}
