{
    "slug": "humblebundle",
    "relevant-countries": [
        "all"
    ],
    "categories": [
        "commerce",
        "entertainment"
    ],
    "name": "Humble Bundle, Inc.",
    "address": "114 Fifth Avenue\n5th Floor\nNew York\nNY 10011\nUnited States of America",
    "phone": "+1 877 948 6253",
    "email": "dpo@humblebundle.com",
    "web": "https://www.humblebundle.com/",
    "sources": [
        "https://www.humblebundle.com/privacy",
        "https://www.bloomberg.com/research/stocks/private/snapshot.asp?privcapid=130405036"
    ],
    "required-elements": [
        {
            "desc": "Name",
            "type": "name"
        },
        {
            "desc": "E-Mail",
            "type": "email"
        }
    ],
    "suggested-transport-medium": "email",
    "needs-id-document": false,
    "request-language": "en",
    "comments": [
        "Support form: https://support.humblebundle.com/hc/en-us/requests/new",
        "Alternative email address: privacy@humblebundle.com"
    ],
    "quality": "tested"
}
