{
    "slug": "infoscore-forderungsmanagement",
    "relevant-countries": [
        "de"
    ],
    "categories": [
        "collection agency"
    ],
    "name": "Riverty Services GmbH",
    "runs": [
        "BFS risk & collection GmbH (ehem.)",
        "Nürnberger Inkasso GmbH (ehem.)",
        "Süd-Westdeutsche Inkasso GmbH (ehem.)",
        "infoscore Forderungsmanagement GmbH (ehem.)"
    ],
    "address": "Gütersloher Straße 123\n33415 Verl\nDeutschland",
    "fax": "+49 5246 9055000",
    "email": "datenschutzbeauftragter@riverty.com",
    "web": "https://de.flow.riverty.com/de-de",
    "sources": [
        "https://de.flow.riverty.com/de-de/impressum",
        "https://github.com/datenanfragen/data/pull/2679"
    ],
    "quality": "verified"
}
