{
    "slug": "memolife",
    "relevant-countries": [
        "de"
    ],
    "categories": [
        "commerce"
    ],
    "name": "memo AG",
    "runs": [
        "https://www.memo.de/",
        "https://www.memo-werbeartikel.de/",
        "https://www.memoworld.de/",
        "https://www.memolife.de/"
    ],
    "address": "Am Biotop 6\n97259 Greußenheim",
    "phone": "+49 9369 905600",
    "fax": "+49 9369 905307",
    "email": "info@memolife.de",
    "web": "https://www.memolife.de",
    "sources": [
        "https://www.memolife.de/datenschutz",
        "https://www.memolife.de/impressum",
        "https://github.com/datenanfragen/data/pull/946"
    ],
    "required-elements": [
        {
            "desc": "Name",
            "type": "name",
            "optional": false
        },
        {
            "desc": "E-Mail-Adresse",
            "type": "email",
            "optional": false
        },
        {
            "desc": "Adresse",
            "type": "address",
            "optional": true
        }
    ],
    "quality": "verified"
}
