{
    "slug": "postbank",
    "categories": [
        "finance"
    ],
    "name": "Deutsche Postbank AG",
    "address": "Friedrich-Ebert-Allee 114 – 126\n53113 Bonn\nDeutschland",
    "phone": "+49 228 920 0",
    "fax": "+49 228 920 35151",
    "email": "direkt@postbank.de",
    "web": "https://www.postbank.de",
    "sources": [
        "https://www.postbank.de/postbank/wu_datenschutz.html",
        "https://www.postbank.de/postbank/wu_impressum.html"
    ],
    "relevant-countries": [
        "de"
    ],
    "quality": "verified"
}
