{
    "slug": "services-totalenergies",
    "relevant-countries": [
        "de"
    ],
    "categories": [
        "utility"
    ],
    "name": "TOTAL Deutschland GmbH",
    "runs": [
        "TotalEnergies",
        "ELAN",
        "MINOL",
        "ACCESS",
        "Total Access",
        "Heizöl"
    ],
    "address": "Jean-Monnet-Str. 2\n10557 Berlin\nDeutschland",
    "phone": "+49 800 8682533",
    "fax": "+49 30 20278833",
    "email": "ms.datenschutz-germany@total.com",
    "web": "https://www.services.totalenergies.de",
    "sources": [
        "https://www.services.totalenergies.de/impressum",
        "https://www.services.totalenergies.de/zentraler-kundenservice",
        "https://services.totalenergies.de/datenschutz",
        "https://heizoel.totalenergies.de/datenschutzerklaerung/",
        "https://github.com/datenanfragen/data/pull/1155"
    ],
    "suggested-transport-medium": "email",
    "quality": "verified"
}
