{
    "slug": "sparda-bank-hannover",
    "categories": [
        "finance"
    ],
    "name": "Sparda-Bank Hannover eG",
    "address": "Simrockstraße 4\n53113 Bonn\nDeutschland",
    "phone": "+49 511 3018 0",
    "fax": "+49 511 3018 100",
    "email": "sparda@sparda-h.de",
    "web": "https://www.sparda-h.de/",
    "sources": [
        "https://www.sparda-h.de/datenschutzhinweise.php",
        "https://www.sparda-h.de/impressum.php"
    ],
    "comments": [
        "Die Sparda-Bank Hannover selbst sitzt: Ernst-August-Platz 8, 30159 Hannover, Deutschland."
    ],
    "relevant-countries": [
        "de"
    ],
    "quality": "verified"
}
