{
    "slug": "xn--gnstiger-reisen-zvb-de",
    "relevant-countries": [
        "de"
    ],
    "categories": [
        "travel"
    ],
    "name": "Günstiger Reisen Reisebüro GmbH",
    "address": "Mariendorfer Damm 147\n12107 Berlin\nDeutschland",
    "phone": "+49 30 994040181",
    "fax": "+49 30 994040183",
    "email": "datenschutz@günstiger-reisen.de",
    "web": "https://www.günstiger-reisen.de",
    "sources": [
        "https://github.com/datenanfragen/data/issues/363",
        "https://www.günstiger-reisen.de/impressum",
        "https://www.günstiger-reisen.de/datenschutz"
    ],
    "required-elements": [
        {
            "desc": "Name",
            "type": "name"
        },
        {
            "desc": "Adresse",
            "type": "address"
        }
    ],
    "suggested-transport-medium": "email"
}
